{"nodes": [{"id": "shared_packages_agent_adapters_tracechain_v1_0_0_tests_unit_conftest_py", "label": "conftest.py", "file_type": "code", "source_file": "shared-packages/agent-adapters-tracechain/v1.0.0/tests/unit/conftest.py", "source_location": "L1"}, {"id": "conftest_credential_config", "label": "credential_config()", "file_type": "code", "source_file": "shared-packages/agent-adapters-tracechain/v1.0.0/tests/unit/conftest.py", "source_location": "L19"}, {"id": "conftest_jwt_config", "label": "jwt_config()", "file_type": "code", "source_file": "shared-packages/agent-adapters-tracechain/v1.0.0/tests/unit/conftest.py", "source_location": "L28"}, {"id": "conftest_fusionauth_config", "label": "fusionauth_config()", "file_type": "code", "source_file": "shared-packages/agent-adapters-tracechain/v1.0.0/tests/unit/conftest.py", "source_location": "L37"}, {"id": "conftest_sample_event", "label": "sample_event()", "file_type": "code", "source_file": "shared-packages/agent-adapters-tracechain/v1.0.0/tests/unit/conftest.py", "source_location": "L54"}, {"id": "conftest_sample_events", "label": "sample_events()", "file_type": "code", "source_file": "shared-packages/agent-adapters-tracechain/v1.0.0/tests/unit/conftest.py", "source_location": "L66"}, {"id": "conftest_token_response_standard", "label": "token_response_standard()", "file_type": "code", "source_file": "shared-packages/agent-adapters-tracechain/v1.0.0/tests/unit/conftest.py", "source_location": "L79"}, {"id": "conftest_fusionauth_login_response", "label": "fusionauth_login_response()", "file_type": "code", "source_file": "shared-packages/agent-adapters-tracechain/v1.0.0/tests/unit/conftest.py", "source_location": "L85"}, {"id": "conftest_token_response_nested", "label": "token_response_nested()", "file_type": "code", "source_file": "shared-packages/agent-adapters-tracechain/v1.0.0/tests/unit/conftest.py", "source_location": "L106"}, {"id": "conftest_stored_event_response", "label": "stored_event_response()", "file_type": "code", "source_file": "shared-packages/agent-adapters-tracechain/v1.0.0/tests/unit/conftest.py", "source_location": "L112"}, {"id": "conftest_batch_response_data", "label": "batch_response_data()", "file_type": "code", "source_file": "shared-packages/agent-adapters-tracechain/v1.0.0/tests/unit/conftest.py", "source_location": "L126"}, {"id": "conftest_verification_response", "label": "verification_response()", "file_type": "code", "source_file": "shared-packages/agent-adapters-tracechain/v1.0.0/tests/unit/conftest.py", "source_location": "L142"}, {"id": "conftest_batch_info_response", "label": "batch_info_response()", "file_type": "code", "source_file": "shared-packages/agent-adapters-tracechain/v1.0.0/tests/unit/conftest.py", "source_location": "L153"}, {"id": "conftest_health_response", "label": "health_response()", "file_type": "code", "source_file": "shared-packages/agent-adapters-tracechain/v1.0.0/tests/unit/conftest.py", "source_location": "L169"}, {"id": "conftest_rationale_1", "label": "Pytest fixtures for ``agent-adapters-tracechain`` unit tests.", "file_type": "rationale", "source_file": "shared-packages/agent-adapters-tracechain/v1.0.0/tests/unit/conftest.py", "source_location": "L1"}, {"id": "conftest_rationale_20", "label": "Build a credential-auth configuration for unit tests.", "file_type": "rationale", "source_file": "shared-packages/agent-adapters-tracechain/v1.0.0/tests/unit/conftest.py", "source_location": "L20"}, {"id": "conftest_rationale_29", "label": "Build a static-JWT configuration for auth-mode tests.", "file_type": "rationale", "source_file": "shared-packages/agent-adapters-tracechain/v1.0.0/tests/unit/conftest.py", "source_location": "L29"}, {"id": "conftest_rationale_38", "label": "Build a FusionAuth login configuration for auth-mode tests.", "file_type": "rationale", "source_file": "shared-packages/agent-adapters-tracechain/v1.0.0/tests/unit/conftest.py", "source_location": "L38"}, {"id": "conftest_rationale_55", "label": "Create a minimal valid event payload for request tests.", "file_type": "rationale", "source_file": "shared-packages/agent-adapters-tracechain/v1.0.0/tests/unit/conftest.py", "source_location": "L55"}, {"id": "conftest_rationale_67", "label": "Return two valid events for batch submission tests.", "file_type": "rationale", "source_file": "shared-packages/agent-adapters-tracechain/v1.0.0/tests/unit/conftest.py", "source_location": "L67"}, {"id": "conftest_rationale_80", "label": "Return a standard top-level auth payload.", "file_type": "rationale", "source_file": "shared-packages/agent-adapters-tracechain/v1.0.0/tests/unit/conftest.py", "source_location": "L80"}, {"id": "conftest_rationale_86", "label": "Return a representative FusionAuth login response.", "file_type": "rationale", "source_file": "shared-packages/agent-adapters-tracechain/v1.0.0/tests/unit/conftest.py", "source_location": "L86"}, {"id": "conftest_rationale_107", "label": "Return a nested auth payload to exercise token extraction.", "file_type": "rationale", "source_file": "shared-packages/agent-adapters-tracechain/v1.0.0/tests/unit/conftest.py", "source_location": "L107"}, {"id": "conftest_rationale_113", "label": "Return a representative stored-event API response.", "file_type": "rationale", "source_file": "shared-packages/agent-adapters-tracechain/v1.0.0/tests/unit/conftest.py", "source_location": "L113"}, {"id": "conftest_rationale_127", "label": "Return a representative batch-submit API response.", "file_type": "rationale", "source_file": "shared-packages/agent-adapters-tracechain/v1.0.0/tests/unit/conftest.py", "source_location": "L127"}, {"id": "conftest_rationale_143", "label": "Return a representative event-verification response.", "file_type": "rationale", "source_file": "shared-packages/agent-adapters-tracechain/v1.0.0/tests/unit/conftest.py", "source_location": "L143"}, {"id": "conftest_rationale_154", "label": "Return a representative batch-info response.", "file_type": "rationale", "source_file": "shared-packages/agent-adapters-tracechain/v1.0.0/tests/unit/conftest.py", "source_location": "L154"}, {"id": "conftest_rationale_170", "label": "Return a representative health-check response.", "file_type": "rationale", "source_file": "shared-packages/agent-adapters-tracechain/v1.0.0/tests/unit/conftest.py", "source_location": "L170"}], "edges": [{"source": "shared_packages_agent_adapters_tracechain_v1_0_0_tests_unit_conftest_py", "target": "datetime", "relation": "imports_from", "confidence": "EXTRACTED", "source_file": "shared-packages/agent-adapters-tracechain/v1.0.0/tests/unit/conftest.py", "source_location": "L5", "weight": 1.0}, {"source": "shared_packages_agent_adapters_tracechain_v1_0_0_tests_unit_conftest_py", "target": "typing", "relation": "imports_from", "confidence": "EXTRACTED", "source_file": "shared-packages/agent-adapters-tracechain/v1.0.0/tests/unit/conftest.py", "source_location": "L6", "weight": 1.0}, {"source": "shared_packages_agent_adapters_tracechain_v1_0_0_tests_unit_conftest_py", "target": "pytest", "relation": "imports", "confidence": "EXTRACTED", "source_file": "shared-packages/agent-adapters-tracechain/v1.0.0/tests/unit/conftest.py", "source_location": "L8", "weight": 1.0}, {"source": "shared_packages_agent_adapters_tracechain_v1_0_0_tests_unit_conftest_py", "target": "agent_adapters_tracechain", "relation": "imports_from", "confidence": "EXTRACTED", "source_file": "shared-packages/agent-adapters-tracechain/v1.0.0/tests/unit/conftest.py", "source_location": "L10", "weight": 1.0}, {"source": "shared_packages_agent_adapters_tracechain_v1_0_0_tests_unit_conftest_py", "target": "conftest_credential_config", "relation": "contains", "confidence": "EXTRACTED", "source_file": "shared-packages/agent-adapters-tracechain/v1.0.0/tests/unit/conftest.py", "source_location": "L19", "weight": 1.0}, {"source": "shared_packages_agent_adapters_tracechain_v1_0_0_tests_unit_conftest_py", "target": "conftest_jwt_config", "relation": "contains", "confidence": "EXTRACTED", "source_file": "shared-packages/agent-adapters-tracechain/v1.0.0/tests/unit/conftest.py", "source_location": "L28", "weight": 1.0}, {"source": "shared_packages_agent_adapters_tracechain_v1_0_0_tests_unit_conftest_py", "target": "conftest_fusionauth_config", "relation": "contains", "confidence": "EXTRACTED", "source_file": "shared-packages/agent-adapters-tracechain/v1.0.0/tests/unit/conftest.py", "source_location": "L37", "weight": 1.0}, {"source": "shared_packages_agent_adapters_tracechain_v1_0_0_tests_unit_conftest_py", "target": "conftest_sample_event", "relation": "contains", "confidence": "EXTRACTED", "source_file": "shared-packages/agent-adapters-tracechain/v1.0.0/tests/unit/conftest.py", "source_location": "L54", "weight": 1.0}, {"source": "shared_packages_agent_adapters_tracechain_v1_0_0_tests_unit_conftest_py", "target": "conftest_sample_events", "relation": "contains", "confidence": "EXTRACTED", "source_file": "shared-packages/agent-adapters-tracechain/v1.0.0/tests/unit/conftest.py", "source_location": "L66", "weight": 1.0}, {"source": "shared_packages_agent_adapters_tracechain_v1_0_0_tests_unit_conftest_py", "target": "conftest_token_response_standard", "relation": "contains", "confidence": "EXTRACTED", "source_file": "shared-packages/agent-adapters-tracechain/v1.0.0/tests/unit/conftest.py", "source_location": "L79", "weight": 1.0}, {"source": "shared_packages_agent_adapters_tracechain_v1_0_0_tests_unit_conftest_py", "target": "conftest_fusionauth_login_response", "relation": "contains", "confidence": "EXTRACTED", "source_file": "shared-packages/agent-adapters-tracechain/v1.0.0/tests/unit/conftest.py", "source_location": "L85", "weight": 1.0}, {"source": "shared_packages_agent_adapters_tracechain_v1_0_0_tests_unit_conftest_py", "target": "conftest_token_response_nested", "relation": "contains", "confidence": "EXTRACTED", "source_file": "shared-packages/agent-adapters-tracechain/v1.0.0/tests/unit/conftest.py", "source_location": "L106", "weight": 1.0}, {"source": "shared_packages_agent_adapters_tracechain_v1_0_0_tests_unit_conftest_py", "target": "conftest_stored_event_response", "relation": "contains", "confidence": "EXTRACTED", "source_file": "shared-packages/agent-adapters-tracechain/v1.0.0/tests/unit/conftest.py", "source_location": "L112", "weight": 1.0}, {"source": "shared_packages_agent_adapters_tracechain_v1_0_0_tests_unit_conftest_py", "target": "conftest_batch_response_data", "relation": "contains", "confidence": "EXTRACTED", "source_file": "shared-packages/agent-adapters-tracechain/v1.0.0/tests/unit/conftest.py", "source_location": "L126", "weight": 1.0}, {"source": "shared_packages_agent_adapters_tracechain_v1_0_0_tests_unit_conftest_py", "target": "conftest_verification_response", "relation": "contains", "confidence": "EXTRACTED", "source_file": "shared-packages/agent-adapters-tracechain/v1.0.0/tests/unit/conftest.py", "source_location": "L142", "weight": 1.0}, {"source": "shared_packages_agent_adapters_tracechain_v1_0_0_tests_unit_conftest_py", "target": "conftest_batch_info_response", "relation": "contains", "confidence": "EXTRACTED", "source_file": "shared-packages/agent-adapters-tracechain/v1.0.0/tests/unit/conftest.py", "source_location": "L153", "weight": 1.0}, {"source": "shared_packages_agent_adapters_tracechain_v1_0_0_tests_unit_conftest_py", "target": "conftest_health_response", "relation": "contains", "confidence": "EXTRACTED", "source_file": "shared-packages/agent-adapters-tracechain/v1.0.0/tests/unit/conftest.py", "source_location": "L169", "weight": 1.0}, {"source": "conftest_rationale_1", "target": "shared_packages_agent_adapters_tracechain_v1_0_0_tests_unit_conftest_py", "relation": "rationale_for", "confidence": "EXTRACTED", "source_file": "shared-packages/agent-adapters-tracechain/v1.0.0/tests/unit/conftest.py", "source_location": "L1", "weight": 1.0}, {"source": "conftest_rationale_20", "target": "conftest_credential_config", "relation": "rationale_for", "confidence": "EXTRACTED", "source_file": "shared-packages/agent-adapters-tracechain/v1.0.0/tests/unit/conftest.py", "source_location": "L20", "weight": 1.0}, {"source": "conftest_rationale_29", "target": "conftest_jwt_config", "relation": "rationale_for", "confidence": "EXTRACTED", "source_file": "shared-packages/agent-adapters-tracechain/v1.0.0/tests/unit/conftest.py", "source_location": "L29", "weight": 1.0}, {"source": "conftest_rationale_38", "target": "conftest_fusionauth_config", "relation": "rationale_for", "confidence": "EXTRACTED", "source_file": "shared-packages/agent-adapters-tracechain/v1.0.0/tests/unit/conftest.py", "source_location": "L38", "weight": 1.0}, {"source": "conftest_rationale_55", "target": "conftest_sample_event", "relation": "rationale_for", "confidence": "EXTRACTED", "source_file": "shared-packages/agent-adapters-tracechain/v1.0.0/tests/unit/conftest.py", "source_location": "L55", "weight": 1.0}, {"source": "conftest_rationale_67", "target": "conftest_sample_events", "relation": "rationale_for", "confidence": "EXTRACTED", "source_file": "shared-packages/agent-adapters-tracechain/v1.0.0/tests/unit/conftest.py", "source_location": "L67", "weight": 1.0}, {"source": "conftest_rationale_80", "target": "conftest_token_response_standard", "relation": "rationale_for", "confidence": "EXTRACTED", "source_file": "shared-packages/agent-adapters-tracechain/v1.0.0/tests/unit/conftest.py", "source_location": "L80", "weight": 1.0}, {"source": "conftest_rationale_86", "target": "conftest_fusionauth_login_response", "relation": "rationale_for", "confidence": "EXTRACTED", "source_file": "shared-packages/agent-adapters-tracechain/v1.0.0/tests/unit/conftest.py", "source_location": "L86", "weight": 1.0}, {"source": "conftest_rationale_107", "target": "conftest_token_response_nested", "relation": "rationale_for", "confidence": "EXTRACTED", "source_file": "shared-packages/agent-adapters-tracechain/v1.0.0/tests/unit/conftest.py", "source_location": "L107", "weight": 1.0}, {"source": "conftest_rationale_113", "target": "conftest_stored_event_response", "relation": "rationale_for", "confidence": "EXTRACTED", "source_file": "shared-packages/agent-adapters-tracechain/v1.0.0/tests/unit/conftest.py", "source_location": "L113", "weight": 1.0}, {"source": "conftest_rationale_127", "target": "conftest_batch_response_data", "relation": "rationale_for", "confidence": "EXTRACTED", "source_file": "shared-packages/agent-adapters-tracechain/v1.0.0/tests/unit/conftest.py", "source_location": "L127", "weight": 1.0}, {"source": "conftest_rationale_143", "target": "conftest_verification_response", "relation": "rationale_for", "confidence": "EXTRACTED", "source_file": "shared-packages/agent-adapters-tracechain/v1.0.0/tests/unit/conftest.py", "source_location": "L143", "weight": 1.0}, {"source": "conftest_rationale_154", "target": "conftest_batch_info_response", "relation": "rationale_for", "confidence": "EXTRACTED", "source_file": "shared-packages/agent-adapters-tracechain/v1.0.0/tests/unit/conftest.py", "source_location": "L154", "weight": 1.0}, {"source": "conftest_rationale_170", "target": "conftest_health_response", "relation": "rationale_for", "confidence": "EXTRACTED", "source_file": "shared-packages/agent-adapters-tracechain/v1.0.0/tests/unit/conftest.py", "source_location": "L170", "weight": 1.0}]}