{"nodes": [{"id": "dev_tools_seeds_index_ts", "label": "index.ts", "file_type": "code", "source_file": "dev-tools/seeds/index.ts", "source_location": "L1"}, {"id": "index_main", "label": "main()", "file_type": "code", "source_file": "dev-tools/seeds/index.ts", "source_location": "L4"}], "edges": [{"source": "dev_tools_seeds_index_ts", "target": "dev_tools_seeds_publish_event", "relation": "imports_from", "confidence": "EXTRACTED", "source_file": "dev-tools/seeds/index.ts", "source_location": "L1", "weight": 1.0}, {"source": "dev_tools_seeds_index_ts", "target": "dev_tools_seeds_get_event_for_command", "relation": "imports_from", "confidence": "EXTRACTED", "source_file": "dev-tools/seeds/index.ts", "source_location": "L2", "weight": 1.0}, {"source": "dev_tools_seeds_index_ts", "target": "index_main", "relation": "contains", "confidence": "EXTRACTED", "source_file": "dev-tools/seeds/index.ts", "source_location": "L4", "weight": 1.0}]}